enrich/__init__.py
enrich/console.py
enrich/logging.py
enrich/py.typed
enrich/test/test_console.py
enrich/test/test_logging.py
enrich-1.2.7.dist-info/LICENSE
enrich-1.2.7.dist-info/METADATA
enrich-1.2.7.dist-info/WHEEL
enrich-1.2.7.dist-info/top_level.txt
enrich-1.2.7.dist-info/RECORD
